aegis_core/__init__.py
aegis_core/detector.py
aegis_core/masker.py
aegis_core/types.py
aegis_core/validators.py
aegis_preflight_core-0.2.2.dist-info/METADATA
aegis_preflight_core-0.2.2.dist-info/WHEEL
aegis_preflight_core-0.2.2.dist-info/RECORD
