Metadata-Version: 2.4
Name: aegis-preflight-core
Version: 0.2.2
Summary: Core detection and masking library for Aegis PII protection
Project-URL: Homepage, https://www.aegispreflight.com/
Project-URL: Documentation, https://docs.aegispreflight.com
Author-email: Aegis Preflight Team <support@aegispreflight.com>
License: Proprietary
Keywords: detection,gdpr,hipaa,masking,pii,privacy
Classifier: Development Status :: 4 - Beta
Classifier: Intended Audience :: Developers
Classifier: License :: Other/Proprietary License
Classifier: Operating System :: OS Independent
Classifier: Programming Language :: Python :: 3
Classifier: Programming Language :: Python :: 3.9
Classifier: Programming Language :: Python :: 3.10
Classifier: Programming Language :: Python :: 3.11
Classifier: Programming Language :: Python :: 3.12
Classifier: Programming Language :: Python :: 3.13
Classifier: Topic :: Security
Classifier: Typing :: Typed
Requires-Python: >=3.9
Provides-Extra: dev
Requires-Dist: pytest-cov>=4.0; extra == 'dev'
Requires-Dist: pytest>=7.0; extra == 'dev'
